simfin/__init__.py
simfin/cache.py
simfin/config.py
simfin/datasets.py
simfin/derived.py
simfin/download.py
simfin/exceptions.py
simfin/hubs.py
simfin/info.py
simfin/load.py
simfin/load_info.py
simfin/names.py
simfin/names_extra.py
simfin/paths.py
simfin/rel_change.py
simfin/resample.py
simfin/signals.py
simfin/transform.py
simfin/utils.py
simfin-1.0.1.dist-info/LICENSE.txt
simfin-1.0.1.dist-info/METADATA
simfin-1.0.1.dist-info/WHEEL
simfin-1.0.1.dist-info/top_level.txt
simfin-1.0.1.dist-info/RECORD
