Metadata-Version: 2.1
Name: simfin
Version: 1.0.1
Summary: Simple financial data for Python
Home-page: https://github.com/simfin/simfin
Author: SimFin
Author-email: info@simfin.com
License: MIT
Keywords: financial data,finance
License-File: LICENSE.txt
